LICENSE
MANIFEST.in
README.md
setup.cfg
setup.py
podiant_tours.egg-info/PKG-INFO
podiant_tours.egg-info/SOURCES.txt
podiant_tours.egg-info/dependency_links.txt
podiant_tours.egg-info/not-zip-safe
podiant_tours.egg-info/top_level.txt
tours/__init__.py
tours/models.py
tours/urls.py
tours/views.py
tours/migrations/0001_initial.py
tours/migrations/0002_auto_20180419_1538.py
tours/migrations/__init__.py