Metadata-Version: 2.1
Name: podiant-tours
Version: 0.1.0
Summary: A simple model to keep track of Bootstrap Tours delivered to new users
Home-page: https://git.steadman.io/podiant/tours
Author: Mark Steadman
Author-email: mark@podiant.co
License: MIT
Keywords: podiant-tours
Platform: UNKNOWN
Classifier: Development Status :: 3 - Alpha
Classifier: Framework :: Django :: 1.11
Classifier: Intended Audience :: Developers
Classifier: License :: OSI Approved :: BSD License
Classifier: Natural Language :: English
Classifier: Programming Language :: Python :: 3
Classifier: Programming Language :: Python :: 3.4
Classifier: Programming Language :: Python :: 3.5
Classifier: Programming Language :: Python :: 3.6
